{"version":"1.0.11-marquee","nodos":[{"id":1,"tipo":"clase","x":121,"y":113.89583206176758,"ancho":252,"alto":154,"minW":160,"minH":90,"titulo":"Inventario","atributos":["id : int pk ai","monto : decimal(10,2)","cambio : decimal(10,2) null","historial : text"],"metodos":["+ metodo(): void"]},{"id":2,"tipo":"clase","x":484,"y":124.89583206176758,"ancho":240,"alto":136,"minW":160,"minH":90,"titulo":"Vendedor","atributos":["id : int pk ai","nombre : String","telefono : Int"],"metodos":["+ metodo(): void"]},{"id":3,"tipo":"clase","x":484,"y":354.8958320617676,"ancho":240,"alto":136,"minW":160,"minH":90,"titulo":"Venta","atributos":["id : int pk ai","nombre : String","monto : decimal(10,2)"],"metodos":["+ metodo(): void"]}],"aristas":[{"id":1762488917495,"origenId":3,"destinoId":1,"anc_o":"izq","anc_d":"abajo","tam":12,"puntos":[],"card_o":"1","card_d":"1..*"},{"id":1762488972641,"origenId":3,"destinoId":2,"anc_o":"arriba","anc_d":"abajo","tam":12,"puntos":[],"card_o":"1","card_d":"1..*"},{"id":1762488991401,"origenId":2,"destinoId":1,"anc_o":"izq","anc_d":"der","tam":12,"puntos":[],"card_o":"1","card_d":"1..*"}],"meta":{"guardado":"2025-11-07T04:16:51.179Z"}}